python_licenses/__init__.py
python_licenses/licenses.py
python_licenses-0.0.1.dist-info/LICENSE
python_licenses-0.0.1.dist-info/METADATA
python_licenses-0.0.1.dist-info/WHEEL
python_licenses-0.0.1.dist-info/top_level.txt
python_licenses-0.0.1.dist-info/RECORD
