Metadata-Version: 2.1
Name: python-licenses
Version: 0.0.1
Summary: A simple way to create and check licenses.
Home-page: https://github.com/SamuelSGSouza/Python-Licenses.git
Author: Samuel G Souza
Author-email: samuels.g.desouza@gmail.com
License: MIT
Platform: UNKNOWN
License-File: LICENSE
